demo/app.py
tvc_demo_flask-0.0.1.dist-info/METADATA
tvc_demo_flask-0.0.1.dist-info/WHEEL
tvc_demo_flask-0.0.1.dist-info/top_level.txt
tvc_demo_flask-0.0.1.dist-info/RECORD
